{
  "PROCESSO": "Número ou identificação do processo judicial",
  "VARA": "Número ou código da vara onde o processo tramita",
  "UF": "Unidade Federativa (estado) do processo",
  "COMARCA": "Nome da comarca (cidade) do processo",
  "TRIBUNAL": "Nome do tribunal responsável",
  "REU": "Nome do réu (parte demandada)",
  "SIGLA": "Sigla ou abreviação associada ao processo ou parte",
  "AUTOR": "Nome do autor (parte autora) do processo",
  "PROCESSO_SECUNDARIO": "Identificação de processo secundário relacionado",
  "STATUS_DO_PROCESSO": "Descrição do status atual do processo",
  "STATUS": "Status geral do processo",
  "COBRANCA_PELA_ANALISE": "Indicador se há cobrança pela análise (S/None)",
  "NUMERO_ORIGINAL_ENVIADO_DIFERENTE_DO_CORRETO": "Flag indicando divergência no número original enviado",
  "NUMERO_ORIGINAL": "Número original do processo antes de correções",
  "NOME_DO_SISTEMA": "Nome do sistema de origem do registro",
  "OBSERVACOES": "Campo livre para observações adicionais",
  "GRUPO_EMPRESARIAL": "Nome do grupo empresarial ao qual a empresa pertence",
  "EMPRESA": "Nome da empresa envolvida no processo",
  "CNPJ": "CNPJ da empresa envolvida",
  "IMPULSIONADOR": "Usuário ou sistema que impulsionou a criação do registro",
  "PROCESSO_ATIVO": "Indicador se o processo está ativo (S/None)",
  "PROCESSO_ATIVO_1": "Descrição textual do estado de atividade do processo",
  "MOTIVO_DO_DESCARTE": "Motivo para descarte ou encerramento do processo",
  "FASE_WORKFLOW": "Fase atual do workflow associado ao processo",
  "DATA_ULTIMO_MOVIMENTO_FLUXO": "Data do último movimento no workflow",
  "USUARIO_DE_CADASTRO": "Usuário que cadastrou o registro",
  "DATA_DE_CADASTRO": "Data de criação do registro",
  "MATERIA": "Matéria ou área do direito do processo",
  "DATA_DE_ATUALIZACAO": "Data e hora da última atualização do registro",
  "IDREGISTRO": "Identificador interno único do registro",
  "PROCESSOSVINCULADOS": "Lista em formato JSON de processos vinculados ao registro",
  "OBJETO": "Tipo de registro (ex.: Desbloqueios)",
  "BANCO": "Nome da instituição bancária",
  "AGENCIA": "Código da agência bancária",
  "CONTA": "Número da conta bancária",
  "VALOR": "Valor bloqueado ou desbloqueado (R$)",
  "VALOR_DESBLOQUEADO_DIVERSO_DO_PETICIONADO": "Valor desbloqueado diferente do solicitado",
  "VALOR_ORIGINALMENTE_PETICIONADO": "Valor originalmente solicitado para desbloqueio",
  "STATUS_DO_BLOQUEIO": "Situação atual do bloqueio (ex.: NÃO DESBLOQUEADO)",
  "DATA_DA_BAIXA_FINALIZACAO": "Data de conclusão da baixa",
  "PASTA_IILEX": "Caminho da pasta no repositório IILEX",
  "RESPONSAVEL_FATURAMENTO_CLIENTE": "Responsável pelo faturamento do cliente",
  "CNPJ_FATURAMENTO_CLIENTE": "CNPJ do cliente faturado",
  "RESPONSAVEL_PELO_FATURAMENTO_VML": "Responsável pelo faturamento interno (VML)",
  "FORMA_DE_ENVIO_AO_PC": "Método de envio ao PC",
  "DATA_ENVIO_PC": "Data de envio ao PC",
  "LOTE_PRESTACAO_DE_CONTAS": "Identificador do lote de prestação de contas"
}